{"name":"t:sections.header.name","type":"header","sections":{"header":{"type":"header","settings":{"logo_position":"middle-center","mobile_logo_position":"center","menu":"main-menu","menu_type_desktop":"dropdown","sticky_header_type":"on-scroll-up","show_line_separator":false,"full_width_header":false,"header_horizontal_padding":0,"enable_top_border":false,"top_border_width":1,"top_border_style":"solid","top_border_color":"#e0e0e0","menu_underline_thickness":1,"menu_underline_color":"#141720","use_theme_colors":true,"use_global_gradient":true,"enable_country_selector":false,"enable_language_selector":false,"enable_customer_avatar":false,"cart_icon_type":"cart","margin_bottom":0,"padding_top":0,"padding_bottom":0}},"scrolling_features_bar_J64Pwx":{"type":"scrolling-features-bar","blocks":{"feature_item_4AhQrK":{"type":"feature_item","settings":{"text":"SPRING SALE — 40% OFF FLY TRAPS | STOCK UP BEFORE FLY SEASON PEAKS","icon_type":"image","icon":""}}},"block_order":["feature_item_4AhQrK"],"name":"Scrolling Features Bar","settings":{"theme_color_mode":"theme_default","vertical_padding":15,"item_gap":40,"mobile_item_gap":30,"font_size":16,"mobile_font_size":14,"letter_spacing":0,"uppercase_text":false,"override_bold":false,"icon_size":20,"mobile_icon_size":16,"icon_spacing":20,"slider_direction":"left","scrolling_velocity":40,"pause_on_hover":false,"background_color":"#ffffff","text_color":"#141720","icon_color":"#000000","use_gradient_background":false,"background_gradient":"","enable_top_border":false,"top_border_width":1,"top_border_style":"solid","top_border_color":"#000000","enable_bottom_border":false,"bottom_border_width":1,"bottom_border_style":"solid","bottom_border_color":"#000000"}}},"order":["header","scrolling_features_bar_J64Pwx"]}